django_gbasedbtdb/__init__.py
django_gbasedbtdb/base.py
django_gbasedbtdb/client.py
django_gbasedbtdb/compiler.py
django_gbasedbtdb/creation.py
django_gbasedbtdb/datatypes.py
django_gbasedbtdb/features.py
django_gbasedbtdb/fields.py
django_gbasedbtdb/introspection.py
django_gbasedbtdb/operations.py
django_gbasedbtdb/schema.py
django_gbasedbtdb/tableignore.py
django_gbasedbtdb/utils.py
test/__init__.py
test/conftest.py
test/test_base.py
test/test_integration.py
test/urls.py
test/datatypes/__init__.py
test/datatypes/models.py
test/datatypes/test_datatypes.py
django_gbasedbtdb-1.10.2.dist-info/LICENSE
django_gbasedbtdb-1.10.2.dist-info/METADATA
django_gbasedbtdb-1.10.2.dist-info/WHEEL
django_gbasedbtdb-1.10.2.dist-info/top_level.txt
django_gbasedbtdb-1.10.2.dist-info/RECORD
