Metadata-Version: 2.1
Name: django_gbasedbtdb
Version: 1.10.2
Summary: A database driver for Django to connect to an GBase 8s database via ODBC
Home-page: https://gbasedbt.com
Author: liaosnet
Author-email: liaosnet@gbasedbt.com
License: APLv2
Keywords: django gbasedbt
Classifier: Development Status :: 5 - Production/Stable
Classifier: Intended Audience :: Developers
Classifier: Topic :: Software Development
Classifier: Topic :: Scientific/Engineering
Classifier: License :: OSI Approved :: Apache Software License
Classifier: Programming Language :: Python :: 3
Classifier: Programming Language :: Python :: 3.6
Classifier: Programming Language :: Python :: 3.7
Classifier: Programming Language :: Python :: 3.8
Classifier: Programming Language :: Python :: 3.9
License-File: LICENSE
Requires-Dist: django<4,>=2.2.0
Requires-Dist: pyodbc~=4.0.21
Provides-Extra: dev
Requires-Dist: check-manifest; extra == "dev"
Provides-Extra: test
Requires-Dist: coverage; extra == "test"
